{"cameraMode":{"drawMode":0,"name":"Shaded","section":"Shading Mode"},"sceneLighting":true,"audioPlay":false,"sceneViewState":{"showFog":true,"showMaterialUpdate":false,"showSkybox":true,"showFlares":true,"showImageEffects":true,"showParticleSystems":true},"in2DMode":false,"pivot":{"x":-128.1510009765625,"y":132.1564178466797,"z":-188.6402130126953},"rotation":{"x":0.09508493542671204,"y":-0.4358857572078705,"z":-0.04398689046502113,"w":-0.8942396640777588},"size":4.856113910675049,"orthographic":false}